xi_method/__init__.py
xi_method/data/bottle.csv
xi_method/data/winequality-red.csv
xi_method/exceptions.py
xi_method/plotting/__init__.py
xi_method/plotting/plot.py
xi_method/separation/__init__.py
xi_method/separation/measurement.py
xi_method/utils.py
xi_method/ximp.py
xi_method-0.1.7.dist-info/LICENSE
xi_method-0.1.7.dist-info/METADATA
xi_method-0.1.7.dist-info/WHEEL
xi_method-0.1.7.dist-info/RECORD
