Metadata-Version: 2.1
Name: xi-method
Version: 0.1.7
Summary: Post hoc explanations for ML models through measures of statistical dependence
Home-page: https://github.com/mfumagalli68/xi-method
License: MIT
Keywords: XaI,explainable,AI
Author: marco.fumagalli
Author-email: m.fumagalli68@gmail.com
Maintainer: marco.fumagalli
Maintainer-email: m.fumagalli68@gmail.com
Requires-Python: >=3.8
Classifier: License :: OSI Approved :: MIT License
Classifier: Programming Language :: Python :: 3
Classifier: Programming Language :: Python :: 3.8
Classifier: Programming Language :: Python :: 3.9
Classifier: Programming Language :: Python :: 3.10
Classifier: Programming Language :: Python :: 3.11
Classifier: Topic :: Scientific/Engineering :: Artificial Intelligence
Classifier: Topic :: Software Development :: Build Tools
Classifier: Topic :: Software Development :: Libraries :: Python Modules
Requires-Dist: matplotlib (>=3.7.2,<4.0.0)
Requires-Dist: numpy (>=1.23.2,<2.0.0)
Requires-Dist: pandas (>=2.0.3,<3.0.0)
Requires-Dist: pytest (>=7.0,<8.0)
Requires-Dist: scipy (>=1.10.0,<2.0.0) ; python_version >= "3.8" and python_version < "3.9"
Requires-Dist: scipy (>=1.11.2,<2.0.0) ; python_version >= "3.10" and python_version < "3.11"
Requires-Dist: scipy (>=1.11.2,<2.0.0) ; python_version >= "3.11" and python_version < "3.12"
Requires-Dist: scipy (>=1.11.2,<2.0.0) ; python_version >= "3.9" and python_version < "3.10"
Requires-Dist: tqdm (>=4.66.1,<5.0.0)
Project-URL: Repository, https://github.com/mfumagalli68/xi-method
